README
setup.py
oshift/__init__.py
oshift/utils.py
oshift.egg-info/PKG-INFO
oshift.egg-info/SOURCES.txt
oshift.egg-info/dependency_links.txt
oshift.egg-info/entry_points.txt
oshift.egg-info/pbr.json
oshift.egg-info/requires.txt
oshift.egg-info/top_level.txt
tests/__init__.py
tests/apps.py
tests/domain.py
tests/user.py