Metadata-Version: 1.0
Name: oshift
Version: 0.2.3
Summary: This is a python interface for the new Openshift REST API.
Home-page: https://github.com/openshift/python-interface
Author: Peter Ruan
Author-email: pruan@redhat.com
License: Apache v2
Keywords: PaaS Redhat OpenShift
Platform: UNKNOWN
